MANIFEST.in
README.rst
setup.py
daemonify/__init__.py
daemonify/daemon.py
daemonify.egg-info/PKG-INFO
daemonify.egg-info/SOURCES.txt
daemonify.egg-info/dependency_links.txt
daemonify.egg-info/top_level.txt
include/daemonify.jpg