Metadata-Version: 1.0
Name: daemonify
Version: 0.1
Summary: daemonify: Python Daemon Class
Home-page: https://github.com/amiralis/daemonify
Author: Amirali Sanatinia
Author-email: amirali@ccs.neu.edu
License: UNKNOWN
Platform: UNKNOWN
